example_pkg/__init__.py
example_pkg/code_file.py
third_python_package-0.0.1.dist-info/METADATA
third_python_package-0.0.1.dist-info/WHEEL
third_python_package-0.0.1.dist-info/top_level.txt
third_python_package-0.0.1.dist-info/RECORD
