Metadata-Version: 2.1
Name: third-python-package
Version: 0.0.1
Summary: My package in python
Home-page: https://github.com/pypa/sampleproject
Author: Nitin Berwal
Author-email: nnitin_be17@thapar.edu
License: UNKNOWN
Platform: UNKNOWN
Requires-Python: >=3.6
